send-sms
setup.py
SMSForward/__init__.py
SMSForward.egg-info/PKG-INFO
SMSForward.egg-info/SOURCES.txt
SMSForward.egg-info/dependency_links.txt
SMSForward.egg-info/requires.txt
SMSForward.egg-info/top_level.txt
SMSForward/providers/MobileFreeFr.py
SMSForward/providers/__init__.py
SMSForward/providers/provider.py