Metadata-Version: 1.0
Name: SMSForward
Version: 0.1
Summary: Forward some message over SMS
Home-page: https://github.com/ivoire/SMSForward
Author: Remi Duraffort
Author-email: remi.duraffort@gmail.com
License: GPL
Platform: UNKNOWN
